{
    "openFiles": [
        {
            "file": {
                "name": "QuickSort.cpp",
                "size": 1196,
                "path": "QuickSort.cpp",
                "fileExtension": ".cpp",
                "isFolder": false,
                "isOpen": false,
                "level": 2,
                "parentPath": "G:\\GitHub\\leetcode\\QuickSort"
            },
            "currentShow": false,
            "isPreview": false,
            "isChange": false
        }
    ],
    "previewName": "QuickSort.cpp",
    "currentShowName": "QuickSort.cpp"
}